gemseo/__init__.py
gemseo/typing.py
gemseo/algos/__init__.py
gemseo/algos/_hdf_database.py
gemseo/algos/_unsuitability_reason.py
gemseo/algos/_variable.py
gemseo/algos/base_algo_factory.py
gemseo/algos/base_algorithm_library.py
gemseo/algos/base_algorithm_settings.py
gemseo/algos/base_driver_library.py
gemseo/algos/base_driver_settings.py
gemseo/algos/base_problem.py
gemseo/algos/constraint_tolerances.py
gemseo/algos/database.py
gemseo/algos/design_space.py
gemseo/algos/design_space_factory.py
gemseo/algos/design_space_utils.py
gemseo/algos/driver_library.py
gemseo/algos/evaluation_counter.py
gemseo/algos/evaluation_problem.py
gemseo/algos/hashable_ndarray.py
gemseo/algos/lagrange_multipliers.py
gemseo/algos/multiobjective_optimization_result.py
gemseo/algos/optimization_history.py
gemseo/algos/optimization_problem.py
gemseo/algos/optimization_result.py
gemseo/algos/parameter_space.py
gemseo/algos/parameter_space_factory.py
gemseo/algos/post_optimal_analysis.py
gemseo/algos/problem_function.py
gemseo/algos/stop_criteria.py
gemseo/algos/_progress_bar/__init__.py
gemseo/algos/_progress_bar/base.py
gemseo/algos/_progress_bar/custom.py
gemseo/algos/_progress_bar/standard.py
gemseo/algos/_progress_bar/unsuffixed.py
gemseo/algos/aggregation/__init__.py
gemseo/algos/aggregation/aggregation_func.py
gemseo/algos/aggregation/core.py
gemseo/algos/doe/__init__.py
gemseo/algos/doe/base_doe.py
gemseo/algos/doe/base_doe_library.py
gemseo/algos/doe/base_doe_settings.py
gemseo/algos/doe/base_full_factorial_doe.py
gemseo/algos/doe/base_n_samples_based_doe_settings.py
gemseo/algos/doe/doe_quality.py
gemseo/algos/doe/factory.py
gemseo/algos/doe/custom_doe/__init__.py
gemseo/algos/doe/custom_doe/custom_doe.py
gemseo/algos/doe/custom_doe/settings/__init__.py
gemseo/algos/doe/custom_doe/settings/custom_doe_settings.py
gemseo/algos/doe/diagonal_doe/__init__.py
gemseo/algos/doe/diagonal_doe/diagonal_doe.py
gemseo/algos/doe/diagonal_doe/settings/__init__.py
gemseo-6.3.0.dist-info/licenses/LICENSE.txt
gemseo-6.3.0.dist-info/METADATA
gemseo-6.3.0.dist-info/WHEEL
gemseo-6.3.0.dist-info/entry_points.txt
gemseo-6.3.0.dist-info/top_level.txt
gemseo-6.3.0.dist-info/RECORD
