Metadata-Version: 2.4
Name: gemseo
Version: 6.3.0
Summary: Generic Engine for Multi-disciplinary Scenarios, Exploration and Optimization
Author-email: GEMSEO developers <contact@gemseo.org>
License-Expression: LGPL-3.0
Project-URL: Homepage, https://gemseo.org
Project-URL: Documentation, https://gemseo.readthedocs.io
Project-URL: Source, https://gitlab.com/gemseo/dev/gemseo
Project-URL: Issues, https://gitlab.com/gemseo/dev/gemseo/-/issues
Classifier: Intended Audience :: Science/Research
Classifier: Topic :: Scientific/Engineering
Classifier: Operating System :: POSIX :: Linux
Classifier: Operating System :: MacOS
Classifier: Operating System :: Microsoft :: Windows
Classifier: Programming Language :: Python :: 3 :: Only
Classifier: Programming Language :: Python :: 3.10
Classifier: Programming Language :: Python :: 3.11
Classifier: Programming Language :: Python :: 3.12
Classifier: Programming Language :: Python :: 3.13
Requires-Python: <3.14,>=3.10
License-File: LICENSE.txt
Requires-Dist: docstring-inheritance<=2.2.2,>=2.0.0
Requires-Dist: fastjsonschema<=2.21.2,>=2.14.5
Requires-Dist: genson<=1.3.0,>=1.2.2
Requires-Dist: h5py<=3.14.0,>=3.6.0
Requires-Dist: jinja2<=3.1.6,>=3.0.0
Requires-Dist: matplotlib<=3.10.6,>=3.6.0
Requires-Dist: networkx<=3.5,>=2.5
Requires-Dist: numpy<=2.3.3,>=1.23
Requires-Dist: packaging<=25,>=15
Requires-Dist: pandas<=2.3.2,>=2.1.0
Requires-Dist: prettytable<=3.16.0,>=2.3.0
Requires-Dist: pyxdsm<=2.3.1,>=2.2.1
Requires-Dist: pydantic<=2.11.9,>=2.7
Requires-Dist: pydantic-settings<=2.11.0,>=2.1.0
Requires-Dist: requests<3,>2
Requires-Dist: scipy<=1.15.2,>=1.12
Requires-Dist: strenum<=0.4.15,>=0.4.9
Requires-Dist: tqdm<=4.67.1,>=4.50
Requires-Dist: typing-extensions<5,>=4
Requires-Dist: xdsmjs<=2.0.0,>=1.0.0
Requires-Dist: xxhash<=3.5.0,>=3.0.0
Requires-Dist: minisom<2.4,>=2.3.5
Provides-Extra: all
Requires-Dist: graphviz<=0.21,>=0.19; extra == "all"
Requires-Dist: nlopt<=2.9.1,>=2.7.0; extra == "all"
Requires-Dist: openpyxl<=3.1.5,>=3.0.10; extra == "all"
Requires-Dist: openturns<=1.25,>=1.20; extra == "all"
Requires-Dist: pillow<=11.3.0,>=9.5.0; extra == "all"
Requires-Dist: plotly<=6.3.0,>=5.7.0; extra == "all"
Requires-Dist: pyDOE3<=1.4.0,>=1.0.1; extra == "all"
Requires-Dist: scikit-learn<=1.7.2,>=1.2; extra == "all"
Requires-Dist: spgl1<=1.0.0,>=0.0.3; extra == "all"
Requires-Dist: sympy<=1.14.0,>=1.5; extra == "all"
Requires-Dist: xlwings<=0.33.16,>=0.27.0; platform_system == "Windows" and extra == "all"
Dynamic: license-file
